Metadata-Version: 1.1
Name: django-tasktracker
Version: 0.2
Summary: A basic Django app to record and track XP stories and tasks.
Home-page: https://gitlab.com/Sidet/XP-task-tracker
Author: Vytenis Gustainis
Author-email: vytenis@gustainis.eu
License: MIT License
Platform: UNKNOWN
Classifier: Environment :: Web Environment
Classifier: Framework :: Django
Classifier: Framework :: Django :: 2.0
Classifier: Intended Audience :: Developers
Classifier: License :: OSI Approved :: MIT License
Classifier: Operating System :: OS Independent
Classifier: Programming Language :: Python
Classifier: Programming Language :: Python :: 3.5
Classifier: Programming Language :: Python :: 3.6
Classifier: Topic :: Internet :: WWW/HTTP
Classifier: Topic :: Internet :: WWW/HTTP :: Dynamic Content
